{"products":[{"company_name":"深圳佰晟泰科技有限公司","image_url":"//cbu01.alicdn.com/img/ibank/2018/840/447/8206744048_207704770.search.jpg","name":"2018新款宠物电子围栏  二合一训狗器 止吠器 户外无线电子围栏","price":218.0,"url":"https://detail.1688.com/offer/563878417612.html"},{"company_name":"深圳佰晟泰科技有限公司","image_url":"//cbu01.alicdn.com/img/ibank/2018/020/793/8701397020_207704770.search.jpg","name":"2018新款训狗器 止吠器 自动止吠器 防水充电电击震动止吠器","price":82.0,"url":"https://detail.1688.com/offer/566904791443.html"},{"company_name":"深圳佰晟泰科技有限公司","image_url":"//cbu01.alicdn.com/img/ibank/2018/395/130/8788031593_207704770.search.jpg","name":"2018年新款 宠物无线电子围栏 宠物电子围栏 训狗器 止吠器","price":320.0,"url":"https://detail.1688.com/offer/568002354359.html"},{"company_name":"深圳佰晟泰科技有限公司","image_url":"//cbu01.alicdn.com/img/ibank/2018/487/485/8752584784_207704770.search.jpg","name":"2018新款 宠物电子围栏 无线电子围栏 训狗器 止吠器 宠物用品","price":180.0,"url":"https://detail.1688.com/offer/568002354164.html"},{"company_name":"深圳佰晟泰科技有限公司","image_url":"//cbu01.alicdn.com/img/ibank/2018/293/967/8725769392_207704770.search.jpg","name":"厂家批发训狗器 宠物用品 止吠器 宠物狗电子震动止吠器 7档灵敏","price":22.0,"url":"https://detail.1688.com/offer/567207791218.html"},{"company_name":"深圳佰晟泰科技有限公司","image_url":"//cbu01.alicdn.com/img/ibank/2018/109/566/8680665901_207704770.search.jpg","name":"最新款电子训狗器 遥控充电宠物训练用品 无线止吠器电击项圈伸缩","price":115.0,"url":"https://detail.1688.com/offer/567001878330.html"},{"company_name":"深圳佰晟泰科技有限公司","image_url":"//cbu01.alicdn.com/img/ibank/2018/133/716/8680617331_207704770.search.jpg","name":"宠物训练用品 防水可充电止吠器训狗器 可伸缩项圈300米遥控电击","price":68.0,"url":"https://detail.1688.com/offer/566918305172.html"},{"company_name":"深圳佰晟泰科技有限公司","image_url":"//cbu01.alicdn.com/img/ibank/2018/309/913/8701319903_207704770.search.jpg","name":"2018最新款充电防水止吠器智能狗叫识别技术防止误触发多种颜色选","price":82.0,"url":"https://detail.1688.com/offer/566815826954.html"},{"company_name":"深圳佰晟泰科技有限公司","image_url":"//cbu01.alicdn.com/img/ibank/2017/194/301/4358103491_207704770.search.jpg","name":"新款自动止吠器 遥控训狗器 二合一宠物无线围栏","price":180.0,"url":"https://detail.1688.com/offer/554015251049.html"},{"company_name":"深圳佰晟泰科技有限公司","image_url":"//cbu01.alicdn.com/img/ibank/2017/557/914/5939419755_207704770.search.jpg","name":"亚马逊爆款第三代室外超声波止吠器 超声波驱狗器 训狗练器","price":55.0,"url":"https://detail.1688.com/offer/561245089253.html"},{"company_name":"深圳佰晟泰科技有限公司","image_url":"//cbu01.alicdn.com/img/ibank/2017/603/012/4567210306_207704770.search.jpg","name":"新款训狗器止吠器电击项圈智能感应电击震动可充电亚马逊爆款","price":82.0,"url":"https://detail.1688.com/offer/557168576046.html"},{"company_name":"深圳佰晟泰科技有限公司","image_url":"//cbu01.alicdn.com/img/ibank/2017/780/687/3890786087_207704770.search.jpg","name":"升级版室外超声波止吠器 超声波止吠器  新型驱狗器 新款训狗器","price":80.0,"url":"https://detail.1688.com/offer/545755616815.html"},{"company_name":"深圳佰晟泰科技有限公司","image_url":"//cbu01.alicdn.com/img/ibank/2017/716/093/4443390617_207704770.search.jpg","name":"新款 宠物无线电子围栏 二合一训狗器无线围栏 止吠器","price":210.0,"url":"https://detail.1688.com/offer/555589955826.html"},{"company_name":"深圳佰晟泰科技有限公司","image_url":"//cbu01.alicdn.com/img/ibank/2017/653/854/4110458356_207704770.search.jpg","name":"新品无线电子围栏 训狗器 止吠器 无线训导器 宠物电子围栏660B","price":180.0,"url":"https://detail.1688.com/offer/549117652503.html"},{"company_name":"深圳佰晟泰科技有限公司","image_url":"//cbu01.alicdn.com/img/ibank/2017/577/176/7585671775_207704770.search.jpg","name":"2017年新款室外超声波驱狗器 三代室外超声波止吠器 训狗器","price":55.0,"url":"https://detail.1688.com/offer/562585612498.html"},{"company_name":"深圳佰晟泰科技有限公司","image_url":"//cbu01.alicdn.com/img/ibank/2017/796/632/4564236697_207704770.search.jpg","name":"新款无电击节止吠器 数码显示止吠器 训狗器 宠物用品 狗狗牵引","price":70.0,"url":"https://detail.1688.com/offer/557292519031.html"},{"company_name":"深圳佰晟泰科技有限公司","image_url":"//cbu01.alicdn.com/img/ibank/2017/666/369/4565963666_207704770.search.jpg","name":"新款数码显示 止吠器 训狗器 超声波止吠 狗项圈颈圈165A","price":82.0,"url":"https://detail.1688.com/offer/557187905662.html"},{"company_name":"深圳佰晟泰科技有限公司","image_url":"//cbu01.alicdn.com/img/ibank/2017/477/806/4563608774_207704770.search.jpg","name":"2017新款潜水训狗器 蓝屏训狗器 止吠器 训犬器","price":210.0,"url":"https://detail.1688.com/offer/557147240517.html"},{"company_name":"深圳佰晟泰科技有限公司","image_url":"//cbu01.alicdn.com/img/ibank/2016/350/065/3049560053_207704770.search.jpg","name":"新款蓝牙手机宠物训练器 止吠 防丢器 电子围栏 3合1","price":280.0,"url":"https://detail.1688.com/offer/531824179467.html"},{"company_name":"深圳佰晟泰科技有限公司","image_url":"//cbu01.alicdn.com/img/ibank/2016/049/325/3047523940_207704770.search.jpg","name":"新款狗狗止吠器 遥控训狗器 自动止吠器 宠物用品PTS610 训狗器","price":175.0,"url":"https://detail.1688.com/offer/531883505757.html"},{"company_name":"深圳佰晟泰科技有限公司","image_url":"//cbu01.alicdn.com/img/ibank/2016/123/453/3278354321_207704770.search.jpg","name":"新款自动止吠器 可充电防水狗项圈 4档位震动电击调节训练器","price":110.0,"url":"https://detail.1688.com/offer/531883045522.html"},{"company_name":"深圳佰晟泰科技有限公司","image_url":"//cbu01.alicdn.com/img/ibank/2016/069/239/3044932960_207704770.search.jpg","name":"全新热销训狗器 止吠器 4合一功能高端训练器","price":145.0,"url":"https://detail.1688.com/offer/531882369540.html"},{"company_name":"深圳佰晟泰科技有限公司","image_url":"//cbu01.alicdn.com/img/ibank/2016/645/552/3278255546_207704770.search.jpg","name":"全新爆款电子项圈狗狗训练器止吠器 训狗器手自动一体可充电防水","price":180.0,"url":"https://detail.1688.com/offer/531800479260.html"},{"company_name":"深圳佰晟泰科技有限公司","image_url":"//cbu01.alicdn.com/img/ibank/2016/656/401/3006104656_207704770.search.jpg","name":"外贸原单 大号硅胶宠物垫 猫狗宠物餐垫 防溅防洒防滑硅胶宠物垫","price":30.0,"url":"https://detail.1688.com/offer/531211791890.html"},{"company_name":"深圳佰晟泰科技有限公司","image_url":"//cbu01.alicdn.com/img/ibank/2016/656/401/3006104656_207704770.search.jpg","name":"厂家直销小号硅胶宠物垫 猫狗宠物餐垫 防溅防洒防滑硅胶宠物垫","price":20.0,"url":"https://detail.1688.com/offer/531288665570.html"},{"company_name":"深圳佰晟泰科技有限公司","image_url":"//cbu01.alicdn.com/img/ibank/2016/797/101/3009101797_207704770.search.jpg","name":"厂家供应 硅胶宠物喂食垫 宠物餐垫 骨形硅胶餐垫 宠物用品","price":31.0,"url":"https://detail.1688.com/offer/531259654755.html"},{"company_name":"深圳佰晟泰科技有限公司","image_url":"//cbu01.alicdn.com/img/ibank/2016/776/578/3007875677_207704770.search.jpg","name":"厂家直销宠物喂食垫 硅胶餐垫 防水狗垫猫垫 车载宠物硅胶垫","price":25.0,"url":"https://detail.1688.com/offer/531262188950.html"},{"company_name":"深圳佰晟泰科技有限公司","image_url":"//cbu01.alicdn.com/img/ibank/2016/159/192/2942291951_207704770.search.jpg","name":"自行车遛狗牵引绳 狗链 狗绳 宠物牵引 宠物用品","price":60.0,"url":"https://detail.1688.com/offer/530489725817.html"},{"company_name":"深圳佰晟泰科技有限公司","image_url":"//cbu01.alicdn.com/img/ibank/2016/159/192/2942291951_207704770.search.jpg","name":"可挂自行车的宠物牵引绳宠物用品 不锈钢牵引器 自行车遛狗牵引器","price":60.0,"url":"https://detail.1688.com/offer/530244200799.html"},{"company_name":"深圳佰晟泰科技有限公司","image_url":"//cbu01.alicdn.com/img/ibank/2016/947/969/3698969749_207704770.search.jpg","name":"厂家直销电子训狗器 自动止吠器 宠物训练器 遥控训狗器JD298","price":160.0,"url":"https://detail.1688.com/offer/526003127026.html"},{"company_name":"深圳佰晟泰科技有限公司","image_url":"//cbu01.alicdn.com/img/ibank/2015/645/714/2623417546_207704770.120x120.jpg","name":"热销款电子训狗器 止吠器 防水可充电宠物训练器 遥控训狗器613","price":100.0,"url":"https://detail.1688.com/offer/524340067476.html"},{"company_name":"深圳佰晟泰科技有限公司","image_url":"//cbu01.alicdn.com/img/ibank/2016/496/493/2713394694_207704770.120x120.jpg","name":"厂家直销遥控训狗器 止吠器 宠物用 电击震动声音训狗器998C","price":44.0,"url":"https://detail.1688.com/offer/525963226131.html"},{"company_name":"深圳佰晟泰科技有限公司","image_url":"//cbu01.alicdn.com/img/ibank/2016/333/488/2886884333_207704770.120x120.jpg","name":"1000米充电防水遥控训狗器 止吠器 电击震动训狗器 宠物用品613","price":115.0,"url":"https://detail.1688.com/offer/529033058791.html"},{"company_name":"深圳佰晟泰科技有限公司","image_url":"//cbu01.alicdn.com/img/ibank/2015/070/659/2634956070_207704770.120x120.jpg","name":"最新款止吠器 高品质训狗器 自动止吠器 遥控训狗器 厂家直销008","price":120.0,"url":"https://detail.1688.com/offer/524669318662.html"},{"company_name":"深圳佰晟泰科技有限公司","image_url":"//cbu01.alicdn.com/img/ibank/2016/069/239/3044932960_207704770.120x120.jpg","name":"全新热销训狗器 止吠器 4合一功能高端训练器","price":145.0,"url":"https://detail.1688.com/offer/531882369540.html"},{"company_name":"深圳佰晟泰科技有限公司","image_url":"//cbu01.alicdn.com/img/ibank/2015/972/832/2705238279_207704770.120x120.jpg","name":"厂家直销宠物用品训练器 训狗器 止吠器 遥控训狗器018","price":160.0,"url":"https://detail.1688.com/offer/524637907974.html"},{"company_name":"深圳佰晟泰科技有限公司","image_url":"//cbu01.alicdn.com/img/ibank/2015/208/593/2630395802_207704770.120x120.jpg","name":"遥控震动止吠器 遥控训狗器 电子训狗器 远距离控制训狗器154","price":44.0,"url":"https://detail.1688.com/offer/524647928547.html"},{"company_name":"深圳佰晟泰科技有限公司","image_url":"//cbu01.alicdn.com/img/ibank/2016/049/325/3047523940_207704770.120x120.jpg","name":"新款狗狗止吠器 遥控训狗器 自动止吠器 宠物用品PTS610 训狗器","price":175.0,"url":"https://detail.1688.com/offer/531883505757.html"},{"company_name":"深圳佰晟泰科技有限公司","image_url":"//cbu01.alicdn.com/img/ibank/2015/136/310/2648013631_207704770.120x120.jpg","name":"户外打猎声音追踪器 遥控电子训狗器 电击震动蜂鸣器 止吠器","price":340.0,"url":"https://detail.1688.com/offer/524831949080.html"},{"company_name":"深圳佰晟泰科技有限公司","image_url":"//cbu01.alicdn.com/img/ibank/2016/611/461/3637164116_207704770.120x120.jpg","name":"新款遥控训狗器 充电防水止吠器 电击震动训狗 器项圈","price":78.0,"url":"https://detail.1688.com/offer/541771675604.html"},{"company_name":"深圳佰晟泰科技有限公司","image_url":"//cbu01.alicdn.com/img/ibank/2015/626/614/2625416626_207704770.120x120.jpg","name":"室外超声波止吠器 室外超声波驱狗器 房子止吠器 训狗器","price":70.0,"url":"https://detail.1688.com/offer/524364699967.html"},{"company_name":"深圳佰晟泰科技有限公司","image_url":"//cbu01.alicdn.com/img/ibank/2015/746/298/2622892647_207704770.120x120.jpg","name":"自动超声波可调节电击止吠器 训狗器 宠物用品 BK208","price":24.0,"url":"https://detail.1688.com/offer/524406524296.html"},{"company_name":"深圳佰晟泰科技有限公司","image_url":"//cbu01.alicdn.com/img/ibank/2016/670/449/2868944076_207704770.120x120.jpg","name":"防狗叫 止吠器 训狗器 超声波止吠 宠物电击狗脖套 自动止吠器853","price":18.0,"url":"https://detail.1688.com/offer/524340878377.html"},{"company_name":"深圳佰晟泰科技有限公司","image_url":"//cbu01.alicdn.com/img/ibank/2016/324/130/3637031423_207704770.120x120.jpg","name":"宠物自动止吠器 声音震动止吠器 无电击止吠器 训狗器","price":21.0,"url":"https://detail.1688.com/offer/541804622157.html"},{"company_name":"深圳佰晟泰科技有限公司","image_url":"//cbu01.alicdn.com/img/ibank/2017/557/914/5939419755_207704770.120x120.jpg","name":"亚马逊爆款第三代室外超声波止吠器 超声波驱狗器 训狗练器","price":55.0,"url":"https://detail.1688.com/offer/561245089253.html"},{"company_name":"深圳佰晟泰科技有限公司","image_url":"//cbu01.alicdn.com/img/ibank/2016/055/064/2870460550_207704770.120x120.jpg","name":"声控电击自动止吠器 超声波止吠器  宠物训练器 训狗器PET-852","price":23.0,"url":"https://detail.1688.com/offer/524785534189.html"},{"company_name":"深圳佰晟泰科技有限公司","image_url":"//cbu01.alicdn.com/img/ibank/2015/633/691/2640196336_207704770.120x120.jpg","name":"厂家直销训狗器 宠物训练器 狗项圈 猎狗蜂鸣器 超声波自动止吠器","price":140.0,"url":"https://detail.1688.com/offer/524786946111.html"},{"company_name":"深圳佰晟泰科技有限公司","image_url":"//cbu01.alicdn.com/img/ibank/2017/603/012/4567210306_207704770.120x120.jpg","name":"新款训狗器止吠器电击项圈智能感应电击震动可充电亚马逊爆款","price":82.0,"url":"https://detail.1688.com/offer/557168576046.html"},{"company_name":"深圳佰晟泰科技有限公司","image_url":"//cbu01.alicdn.com/img/ibank/2017/780/687/3890786087_207704770.120x120.jpg","name":"升级版室外超声波止吠器 超声波止吠器  新型驱狗器 新款训狗器","price":80.0,"url":"https://detail.1688.com/offer/545755616815.html"},{"company_name":"深圳佰晟泰科技有限公司","image_url":"//cbu01.alicdn.com/img/ibank/2015/521/626/2640626125_207704770.120x120.jpg","name":"供应训狗器 超声波止吠器 狗止吠器 自动止吠器PET-850","price":75.0,"url":"https://detail.1688.com/offer/524763201303.html"},{"company_name":"深圳佰晟泰科技有限公司","image_url":"//cbu01.alicdn.com/img/ibank/2016/480/405/3115504084_207704770.120x120.jpg","name":"2016年新款宠物无线电子围栏  宠物训练器 止吠器","price":235.0,"url":"https://detail.1688.com/offer/533662237121.html"},{"company_name":"深圳佰晟泰科技有限公司","image_url":"//cbu01.alicdn.com/img/ibank/2016/195/023/3268320591_207704770.120x120.jpg","name":"新款 无线电子围栏 宠物用品 电子围栏充电防水 训狗器","price":150.0,"url":"https://detail.1688.com/offer/536222308536.html"},{"company_name":"深圳佰晟泰科技有限公司","image_url":"//cbu01.alicdn.com/img/ibank/2016/477/070/3636070774_207704770.120x120.jpg","name":"无线电子围栏 宠物电子围栏 500米半径 接收器不限 防水可充电","price":300.0,"url":"https://detail.1688.com/offer/541756777417.html"},{"company_name":"深圳佰晟泰科技有限公司","image_url":"//cbu01.alicdn.com/img/ibank/2015/600/507/2633705006_207704770.120x120.jpg","name":"厂家直销宠物电子围栏 训狗器  自动止吠器 宠物用品023","price":83.0,"url":"https://detail.1688.com/offer/524670184980.html"},{"company_name":"深圳佰晟泰科技有限公司","image_url":"//cbu01.alicdn.com/img/ibank/2016/547/421/3273124745_207704770.120x120.jpg","name":"最新爆款 宠物电子围栏 宠物用品批发 宠物训练器 狗狗隔离栏批发","price":155.0,"url":"https://detail.1688.com/offer/536253161415.html"},{"company_name":"深圳佰晟泰科技有限公司","image_url":"//cbu01.alicdn.com/img/ibank/2018/840/447/8206744048_207704770.120x120.jpg","name":"2018新款宠物电子围栏  二合一训狗器 止吠器 户外无线电子围栏","price":218.0,"url":"https://detail.1688.com/offer/563878417612.html"},{"company_name":"深圳佰晟泰科技有限公司","image_url":"//cbu01.alicdn.com/img/ibank/2017/716/093/4443390617_207704770.120x120.jpg","name":"新款 宠物无线电子围栏 二合一训狗器无线围栏 止吠器","price":210.0,"url":"https://detail.1688.com/offer/555589955826.html"},{"company_name":"深圳佰晟泰科技有限公司","image_url":"//cbu01.alicdn.com/img/ibank/2017/653/854/4110458356_207704770.120x120.jpg","name":"新品无线电子围栏 训狗器 止吠器 无线训导器 宠物电子围栏660B","price":180.0,"url":"https://detail.1688.com/offer/549117652503.html"},{"company_name":"深圳佰晟泰科技有限公司","image_url":"//cbu01.alicdn.com/img/ibank/2015/611/825/2623528116_207704770.120x120.jpg","name":"供应宠物电子围栏 止吠器 宠物用品 电子宠物用品 训狗器800","price":175.0,"url":"https://detail.1688.com/offer/524464120307.html"},{"company_name":"深圳佰晟泰科技有限公司","image_url":"//cbu01.alicdn.com/img/ibank/2015/989/705/2623507989_207704770.120x120.jpg","name":"最新正品LED充电防水功能 宠物电子围栏 训狗器 止吠器227B","price":148.0,"url":"https://detail.1688.com/offer/524380360464.html"},{"company_name":"深圳佰晟泰科技有限公司","image_url":"//cbu01.alicdn.com/img/ibank/2015/259/085/2666580952_207704770.120x120.jpg","name":"爆款 12LED紫光手电筒 UV紫光手电筒 UV手电筒 厂家直销","price":6.0,"url":"https://detail.1688.com/offer/525222942035.html"},{"company_name":"深圳佰晟泰科技有限公司","image_url":"//cbu01.alicdn.com/img/ibank/2015/458/963/2676369854_207704770.120x120.jpg","name":"UV紫光手电筒 UV紫光灯 铝合金电筒 验钞手电筒 9LED紫光电筒","price":4.8,"url":"https://detail.1688.com/offer/525258619021.html"},{"company_name":"深圳佰晟泰科技有限公司","image_url":"//cbu01.alicdn.com/img/ibank/2015/089/058/2671850980_207704770.120x120.jpg","name":"现货UV手电筒 21LED紫光手电筒 UV验钞灯 紫光LED手电筒 紫光电筒","price":9.5,"url":"https://detail.1688.com/offer/525223623183.html"},{"company_name":"深圳佰晟泰科技有限公司","image_url":"//cbu01.alicdn.com/img/ibank/2015/475/933/2662339574_207704770.120x120.jpg","name":"9LED便携紫光验钞灯手电筒 UV手电筒 UV紫光手电筒 新品批发","price":4.8,"url":"https://detail.1688.com/offer/525138877384.html"},{"company_name":"深圳佰晟泰科技有限公司","image_url":"//cbu01.alicdn.com/img/ibank/2015/036/371/2625173630_207704770.120x120.jpg","name":"厂家直销 21led紫光手电筒 UV手电筒 多功能验钞紫外线手电筒","price":9.5,"url":"https://detail.1688.com/offer/524542737533.html"},{"company_name":"深圳佰晟泰科技有限公司","image_url":"//cbu01.alicdn.com/img/ibank/2015/259/085/2666580952_207704770.120x120.jpg","name":"爆款手电筒12LED紫光手电筒 UV手电筒 12led紫外线手电筒 蝎子灯","price":6.0,"url":"https://detail.1688.com/offer/525138893064.html"},{"company_name":"深圳佰晟泰科技有限公司","image_url":"//cbu01.alicdn.com/img/ibank/2015/818/439/2657934818_207704770.120x120.jpg","name":"厂家直销UV紫光电筒 9LED紫光手电筒 UV多功能验钞手电筒","price":4.8,"url":"https://detail.1688.com/offer/525012780490.html"},{"company_name":"深圳佰晟泰科技有限公司","image_url":"//cbu01.alicdn.com/img/ibank/2015/444/432/2629234444_207704770.120x120.jpg","name":"UV紫光手电筒 UV紫光灯 铝合金电筒 验钞手电筒 21LED紫光电筒","price":9.5,"url":"https://detail.1688.com/offer/524627249324.html"},{"company_name":"深圳佰晟泰科技有限公司","image_url":"//cbu01.alicdn.com/img/ibank/2015/033/543/2631345330_207704770.120x120.jpg","name":"现货UV手电筒 9LED紫光手电筒 UV验钞灯 LED UV紫光手电筒","price":3.0,"url":"https://detail.1688.com/offer/524608908230.html"},{"company_name":"深圳佰晟泰科技有限公司","image_url":"//cbu01.alicdn.com/img/ibank/2015/175/903/2653309571_207704770.120x120.jpg","name":"厂家直销UV手电筒 UV紫光手电筒 UV多功能验钞手电筒 紫外线电筒","price":6.0,"url":"https://detail.1688.com/offer/524597113551.html"},{"company_name":"深圳佰晟泰科技有限公司","image_url":"//cbu01.alicdn.com/img/ibank/2016/983/003/2796300389_207704770.search.jpg","name":"热卖 宠物用品猫门猫洞狗门洞 可控制出入方向宠物门 猫犬舍","price":35.0,"url":"https://detail.1688.com/offer/527645751812.html"},{"company_name":"深圳佰晟泰科技有限公司","image_url":"//cbu01.alicdn.com/img/ibank/2016/792/693/2794396297_207704770.search.jpg","name":"宠物用品 纱窗门 狗门猫门 磁铁定位 大小号","price":33.0,"url":"https://detail.1688.com/offer/527714841285.html"},{"company_name":"深圳佰晟泰科技有限公司","image_url":"//cbu01.alicdn.com/img/ibank/2016/288/252/2794252882_207704770.search.jpg","name":"宠物用品 宠物门 狗狗猫洞 大狗门 可自由进出 控制开关","price":160.0,"url":"https://detail.1688.com/offer/527700082300.html"},{"company_name":"深圳佰晟泰科技有限公司","image_url":"//cbu01.alicdn.com/img/ibank/2016/319/494/2797494913_207704770.search.jpg","name":"批发宠物纱窗门 纱门 猫门狗门猫洞狗洞 防蚊 中小型犬 小号","price":29.0,"url":"https://detail.1688.com/offer/527698206560.html"},{"company_name":"深圳佰晟泰科技有限公司","image_url":"//cbu01.alicdn.com/img/ibank/2016/949/225/2796522949_207704770.search.jpg","name":"宠物用品 宠物门 狗狗猫门 可自由出入 开关控制 小号门","price":15.0,"url":"https://detail.1688.com/offer/527688826254.html"},{"company_name":"深圳佰晟泰科技有限公司","image_url":"//cbu01.alicdn.com/img/ibank/2016/109/742/3636247901_207704770.search.jpg","name":"新品狗毛刷猫咪狗梳子金毛泰迪大中小型犬狗狗褪毛脱毛梳宠物用品","price":22.0,"url":"https://detail.1688.com/offer/541768750161.html"},{"company_name":"深圳佰晟泰科技有限公司","image_url":"//cbu01.alicdn.com/img/ibank/2016/479/314/3033413974_207704770.search.jpg","name":"第五代脱毛梳子 宠物脱毛梳去毛 猫排梳泰迪金毛狗梳子","price":25.0,"url":"https://detail.1688.com/offer/531649574334.html"},{"company_name":"深圳佰晟泰科技有限公司","image_url":"//cbu01.alicdn.com/img/ibank/2016/143/422/3637224341_207704770.search.jpg","name":"宠物梳子 开结梳 猫狗针梳 大中小型犬通用梳子 宠物脱毛梳","price":21.0,"url":"https://detail.1688.com/offer/541767246693.html"},{"company_name":"深圳佰晟泰科技有限公司","image_url":"//cbu01.alicdn.com/img/ibank/2016/475/800/2819008574_207704770.search.jpg","name":"正品行货 得乐宠物祛毛刀 宠物脱毛梳 猫狗梳子 去毛美容用品混批","price":20.0,"url":"https://detail.1688.com/offer/528033667134.html"},{"company_name":"深圳佰晟泰科技有限公司","image_url":"//cbu01.alicdn.com/img/ibank/2016/167/447/2794744761_207704770.search.jpg","name":"自主品牌 专用褪毛梳 宠物脱毛梳子 狗梳子 开结梳 4寸脱毛梳","price":27.0,"url":"https://detail.1688.com/offer/527716725858.html"},{"company_name":"深圳佰晟泰科技有限公司","image_url":"//cbu01.alicdn.com/img/ibank/2016/233/923/2796329332_207704770.search.jpg","name":"自主品牌大型犬5寸宠物刷 宠物脱毛梳 脱毛刷子 宠物梳厂家直销","price":27.0,"url":"https://detail.1688.com/offer/527717005961.html"},{"company_name":"深圳佰晟泰科技有限公司","image_url":"//cbu01.alicdn.com/img/ibank/2016/116/032/2796230611_207704770.search.jpg","name":"2.65寸宠物脱毛梳  褪毛梳 狗梳子宠物梳 厂家直销可混批","price":26.0,"url":"https://detail.1688.com/offer/527733272230.html"},{"company_name":"深圳佰晟泰科技有限公司","image_url":"//cbu01.alicdn.com/img/ibank/2016/621/846/2794648126_207704770.search.jpg","name":"五代梳毛器脱毛梳 大型犬褪毛梳 金毛退毛梳 宠物狗狗梳子1.75寸","price":25.0,"url":"https://detail.1688.com/offer/527716665386.html"},{"company_name":"深圳佰晟泰科技有限公司","image_url":"//cbu01.alicdn.com/img/ibank/2015/277/569/2629965772_207704770.search.jpg","name":"可调节超声波犬笛 狗哨子 宠物狗笛 训犬口哨 训狗器 超声波狗哨","price":3.0,"url":"https://detail.1688.com/offer/524454409373.html"},{"company_name":"深圳佰晟泰科技有限公司","image_url":"//cbu01.alicdn.com/img/ibank/2015/580/795/2662597085_207704770.search.jpg","name":"批发宠物训练笛子 哨子 口哨 狗狗哨子 宠物用品 犬笛","price":3.0,"url":"https://detail.1688.com/offer/525154892693.html"},{"company_name":"深圳佰晟泰科技有限公司","image_url":"//cbu01.alicdn.com/img/ibank/2015/284/900/2667009482_207704770.search.jpg","name":"可调节超声波犬笛 宠物训导用品 宠物狗笛训犬口哨 训狗器 狗哨","price":3.0,"url":"https://detail.1688.com/offer/525142185297.html"},{"company_name":"深圳佰晟泰科技有限公司","image_url":"//cbu01.alicdn.com/img/ibank/2015/782/848/2664848287_207704770.search.jpg","name":"供应宠物训练器带口哨狗狗响片宠物用品响声器口哨","price":2.8,"url":"https://detail.1688.com/offer/525106431645.html"},{"company_name":"深圳佰晟泰科技有限公司","image_url":"//cbu01.alicdn.com/img/ibank/2015/726/479/2629974627_207704770.search.jpg","name":"厂家直销超声波犬笛 训狗口哨 超声波训狗口哨 超声波狗哨子 犬笛","price":3.0,"url":"https://detail.1688.com/offer/524411224556.html"},{"company_name":"深圳佰晟泰科技有限公司","image_url":"//cbu01.alicdn.com/img/ibank/2015/764/961/2645169467_207704770.search.jpg","name":"厂家直销宠物用品多功能宠物响片 狗哨 训狗器 止吠器 犬笛训狗器","price":2.8,"url":"https://detail.1688.com/offer/524805852006.html"},{"company_name":"深圳佰晟泰科技有限公司","image_url":"//cbu01.alicdn.com/img/ibank/2015/301/255/2631552103_207704770.search.jpg","name":"厂家直销可调节超声波犬笛 训狗器 宠物狗哨  犬笛训练 狗哨子","price":3.0,"url":"https://detail.1688.com/offer/524609824629.html"},{"company_name":"深圳佰晟泰科技有限公司","image_url":"//cbu01.alicdn.com/img/ibank/2015/018/620/2627026810_207704770.search.jpg","name":"厂家直销宠物训练器  超声波犬笛 训导用品 超声波狗哨 犬笛训练","price":3.0,"url":"https://detail.1688.com/offer/524566751163.html"},{"company_name":"深圳佰晟泰科技有限公司","image_url":"//cbu01.alicdn.com/img/ibank/2015/361/730/2646037163_207704770.120x120.jpg","name":"厂家直销 四排尖钉狗链 霸气宠物项圈 宠物用品狗圈 狗狗项圈","price":25.0,"url":"https://detail.1688.com/offer/524860786372.html"},{"company_name":"深圳佰晟泰科技有限公司","image_url":"//cbu01.alicdn.com/img/ibank/2015/880/468/2649864088_207704770.120x120.jpg","name":"厂家直销 四排尖钉狗链霸气野性宠物项圈 宠物用品 狗项圈","price":26.0,"url":"https://detail.1688.com/offer/524858994204.html"},{"company_name":"深圳佰晟泰科技有限公司","image_url":"//cbu01.alicdn.com/img/ibank/2015/829/862/2651268928_207704770.120x120.jpg","name":"厂家直销狗项圈 加宽6颗狼牙尖钉宠物项圈 彪悍结实狗链 狗项圈","price":26.0,"url":"https://detail.1688.com/offer/524851527234.html"},{"company_name":"深圳佰晟泰科技有限公司","image_url":"//cbu01.alicdn.com/img/ibank/2015/764/961/2645169467_207704770.120x120.jpg","name":"厂家直销宠物用品多功能宠物响片 狗哨 训狗器 止吠器 犬笛训狗器","price":2.8,"url":"https://detail.1688.com/offer/524805852006.html"},{"company_name":"深圳佰晟泰科技有限公司","image_url":"//cbu01.alicdn.com/img/ibank/2015/133/748/2640847331_207704770.120x120.jpg","name":"自动止吠器 电击震动止吠器 宠物训练器 电子训狗器BT-6","price":45.0,"url":"https://detail.1688.com/offer/524793545607.html"},{"company_name":"深圳佰晟泰科技有限公司","image_url":"//cbu01.alicdn.com/img/ibank/2015/420/998/2644899024_207704770.120x120.jpg","name":"厂家直销可调声控止吠器 训狗器 超声波自动止吠器 宠物用品BS-8","price":19.0,"url":"https://detail.1688.com/offer/524791537355.html"},{"company_name":"深圳佰晟泰科技有限公司","image_url":"//cbu01.alicdn.com/img/ibank/2015/633/691/2640196336_207704770.120x120.jpg","name":"厂家直销训狗器 宠物训练器 狗项圈 猎狗蜂鸣器 超声波自动止吠器","price":140.0,"url":"https://detail.1688.com/offer/524786946111.html"},{"company_name":"深圳佰晟泰科技有限公司","image_url":"//cbu01.alicdn.com/img/ibank/2015/309/280/2640082903_207704770.120x120.jpg","name":"声控电击止吠器 自动止吠器 超声波止吠器 电子训狗器X888","price":83.0,"url":"https://detail.1688.com/offer/524786469240.html"},{"company_name":"深圳佰晟泰科技有限公司","image_url":"//cbu01.alicdn.com/img/ibank/2015/231/508/2640805132_207704770.120x120.jpg","name":"自动训狗器 训狗器 超声波止吠 宠物电击狗脖套 自动止吠器BT-1","price":18.0,"url":"https://detail.1688.com/offer/524758651951.html"},{"company_name":"深圳佰晟泰科技有限公司","image_url":"//cbu01.alicdn.com/img/ibank/2015/021/512/2633215120_207704770.120x120.jpg","name":"厂家直销宠物狗升级版止吠器 自动止吠器 电击声控止吠器BK209","price":22.0,"url":"https://detail.1688.com/offer/524685652131.html"},{"company_name":"深圳佰晟泰科技有限公司","image_url":"//cbu01.alicdn.com/img/ibank/2015/208/593/2630395802_207704770.120x120.jpg","name":"遥控震动止吠器 遥控训狗器 电子训狗器 远距离控制训狗器154","price":44.0,"url":"https://detail.1688.com/offer/524647928547.html"},{"company_name":"深圳佰晟泰科技有限公司","image_url":"//cbu01.alicdn.com/img/ibank/2015/972/832/2705238279_207704770.120x120.jpg","name":"厂家直销宠物用品训练器 训狗器 止吠器 遥控训狗器018","price":160.0,"url":"https://detail.1688.com/offer/524637907974.html"},{"company_name":"深圳佰晟泰科技有限公司","image_url":"//cbu01.alicdn.com/img/ibank/2015/175/903/2653309571_207704770.120x120.jpg","name":"厂家直销UV手电筒 UV紫光手电筒 UV多功能验钞手电筒 紫外线电筒","price":6.0,"url":"https://detail.1688.com/offer/524597113551.html"},{"company_name":"深圳佰晟泰科技有限公司","image_url":"//cbu01.alicdn.com/img/ibank/2015/281/706/2630607182_207704770.120x120.jpg","name":"一拖三300M 遥控训狗器 自动止吠器 电子训狗器 宠物训练器P600","price":130.0,"url":"https://detail.1688.com/offer/524581333697.html"},{"company_name":"深圳佰晟泰科技有限公司","image_url":"//cbu01.alicdn.com/img/ibank/2015/514/136/2630631415_207704770.120x120.jpg","name":"LCD显示电子遥控训狗器 宠物用品 自动止吠器 一拖三训狗器600B","price":150.0,"url":"https://detail.1688.com/offer/524578654989.html"},{"company_name":"深圳佰晟泰科技有限公司","image_url":"//cbu01.alicdn.com/img/ibank/2015/607/244/2625442706_207704770.120x120.jpg","name":"畅销款厂家直销超声波驱狗器 训狗器 止吠器 LED手电筒 驱猫器","price":23.0,"url":"https://detail.1688.com/offer/524542359973.html"},{"company_name":"深圳佰晟泰科技有限公司","image_url":"//cbu01.alicdn.com/img/ibank/2015/314/409/2622904413_207704770.120x120.jpg","name":"宠物用品 自动止吠器 超声波止吠器 宠物训练器 电子训狗器101","price":24.0,"url":"https://detail.1688.com/offer/524405444427.html"},{"company_name":"深圳佰晟泰科技有限公司","image_url":"//cbu01.alicdn.com/img/ibank/2015/286/023/2625320682_207704770.120x120.jpg","name":"厂家供应训狗器 宠物止吠器 自动止吠器 声控电击止吠器 BK017","price":18.0,"url":"https://detail.1688.com/offer/524394666547.html"},{"company_name":"深圳佰晟泰科技有限公司","image_url":"//cbu01.alicdn.com/img/ibank/2015/989/705/2623507989_207704770.120x120.jpg","name":"最新正品LED充电防水功能 宠物电子围栏 训狗器 止吠器227B","price":148.0,"url":"https://detail.1688.com/offer/524380360464.html"},{"company_name":"深圳佰晟泰科技有限公司","image_url":"//cbu01.alicdn.com/img/ibank/2016/319/121/3163121913_207704770.120x120.jpg","name":"批发便携式夜视跟踪野外红外感应相机户外监控摄像机打猎狩猎相机","price":260.0,"url":"https://detail.1688.com/offer/534458640902.html"},{"company_name":"深圳佰晟泰科技有限公司","image_url":"//cbu01.alicdn.com/img/ibank/2015/829/862/2651268928_207704770.search.jpg","name":"厂家直销狗项圈 加宽6颗狼牙尖钉宠物项圈 彪悍结实狗链 狗项圈","price":26.0,"url":"https://detail.1688.com/offer/524851527234.html"},{"company_name":"深圳佰晟泰科技有限公司","image_url":"//cbu01.alicdn.com/img/ibank/2015/345/182/2650281543_207704770.search.jpg","name":"厂家直销 霸气拉风红色黑色金色狗链 尖钉牛角宠物项圈 宠物用品","price":21.0,"url":"https://detail.1688.com/offer/524827755847.html"},{"company_name":"深圳佰晟泰科技有限公司","image_url":"//cbu01.alicdn.com/img/ibank/2015/361/730/2646037163_207704770.search.jpg","name":"厂家直销 四排尖钉狗链 霸气宠物项圈 宠物用品狗圈 狗狗项圈","price":25.0,"url":"https://detail.1688.com/offer/524860786372.html"},{"company_name":"深圳佰晟泰科技有限公司","image_url":"//cbu01.alicdn.com/img/ibank/2015/341/021/2648120143_207704770.search.jpg","name":"厂家直销合金牛角霸气的尖钉宠物项圈 宠物狗链 宠物用品BS072","price":18.0,"url":"https://detail.1688.com/offer/524873128123.html"},{"company_name":"深圳佰晟泰科技有限公司","image_url":"//cbu01.alicdn.com/img/ibank/2015/880/468/2649864088_207704770.search.jpg","name":"厂家直销 四排尖钉狗链霸气野性宠物项圈 宠物用品 狗项圈","price":26.0,"url":"https://detail.1688.com/offer/524858994204.html"},{"company_name":"深圳佰晟泰科技有限公司","image_url":"//cbu01.alicdn.com/img/ibank/2015/607/244/2625442706_207704770.120x120.jpg","name":"畅销款厂家直销超声波驱狗器 训狗器 止吠器 LED手电筒 驱猫器","price":23.0,"url":"https://detail.1688.com/offer/524542359973.html"},{"company_name":"深圳佰晟泰科技有限公司","image_url":"//cbu01.alicdn.com/img/ibank/2015/478/124/2625421874_207704770.120x120.jpg","name":"厂家直销最新加强充电式超声波驱狗器 训狗器 止吠器 LED手电筒","price":36.0,"url":"https://detail.1688.com/offer/524413879992.html"},{"company_name":"深圳佰晟泰科技有限公司","image_url":"//cbu01.alicdn.com/img/ibank/2015/802/729/2627927208_207704770.120x120.jpg","name":"超声波4合1多功能驱狗器 防狼器 防盗报警 训狗器 止吠器J-1003","price":65.0,"url":"https://detail.1688.com/offer/524368563810.html"},{"company_name":"深圳佰晟泰科技有限公司","image_url":"//cbu01.alicdn.com/img/ibank/2015/427/112/2690211724_207704770.search.jpg","name":"2015年亚马逊暴款 自动喂水 宠物脚踏自动喂水器 宠物自动取水器","price":95.0,"url":"https://detail.1688.com/offer/525601956092.html"},{"company_name":"深圳佰晟泰科技有限公司","image_url":"//cbu01.alicdn.com/img/ibank/2015/746/224/2688422647_207704770.search.jpg","name":"宠物饮水器狗狗饮水机喝水器 狗水壶外出自动喂水器狗狗用品","price":95.0,"url":"https://detail.1688.com/offer/525530329496.html"},{"company_name":"深圳佰晟泰科技有限公司","image_url":"//cbu01.alicdn.com/img/ibank/2015/076/989/2629989670_207704770.search.jpg","name":"外贸热销品 宠物脚踩自动取水器 宠物自动喂水器 狗狗喂水器","price":95.0,"url":"https://detail.1688.com/offer/524393933460.html"},{"company_name":"深圳佰晟泰科技有限公司","image_url":"//cbu01.alicdn.com/img/ibank/2015/427/112/2690211724_207704770.search.jpg","name":"自动喂水 2015年亚马逊暴款 宠物脚踏自动喂水器 宠物自动取水器","price":95.0,"url":"https://detail.1688.com/offer/525519787353.html"},{"company_name":"深圳佰晟泰科技有限公司","image_url":"//cbu01.alicdn.com/img/ibank/2016/798/046/2813640897_207704770.summ.jpg","name":"厂家直销3合1激光红外线验钞手电 激光LED激光手电筒","price":3.0,"url":"https://detail.1688.com/offer/527907731827.html"},{"company_name":"深圳佰晟泰科技有限公司","image_url":"//cbu01.alicdn.com/img/ibank/2016/178/383/2813383871_207704770.summ.jpg","name":"厂家直销 笔扣式 迷你LED袖珍小手电 强光手电筒","price":4.0,"url":"https://detail.1688.com/offer/527989570887.html"},{"company_name":"深圳佰晟泰科技有限公司","image_url":"//cbu01.alicdn.com/img/ibank/2016/829/359/2811953928_207704770.summ.jpg","name":"厂家直销 迷你伸缩变焦 登山扣小强光手电筒 促销礼品电子灯","price":2.2,"url":"https://detail.1688.com/offer/527951898029.html"},{"company_name":"深圳佰晟泰科技有限公司","image_url":"//cbu01.alicdn.com/img/ibank/2016/505/640/2810046505_207704770.summ.jpg","name":"厂家直销小电筒 哥伦比亚 迷你登山扣小强光手电筒 登山扣电子灯","price":2.0,"url":"https://detail.1688.com/offer/527931132240.html"},{"company_name":"深圳佰晟泰科技有限公司","image_url":"//cbu01.alicdn.com/img/ibank/2016/054/145/2813541450_207704770.summ.jpg","name":"热销款投影手电筒 logo定制金属投影钥匙扣 LED钥匙扣","price":3.0,"url":"https://detail.1688.com/offer/527907707658.html"},{"company_name":"深圳佰晟泰科技有限公司","image_url":"//cbu01.alicdn.com/img/ibank/2016/442/598/2797895244_207704770.summ.jpg","name":"厂家直销三合一猫玩具激光灯 电子逗猫棒 激光镭射手电筒","price":2.8,"url":"https://detail.1688.com/offer/527748285723.html"},{"company_name":"深圳佰晟泰科技有限公司","image_url":"//cbu01.alicdn.com/img/ibank/2015/361/730/2646037163_207704770.summ.jpg","name":"厂家直销 四排尖钉狗链 霸气宠物项圈 宠物用品狗圈 狗狗项圈","price":25.0,"url":"https://detail.1688.com/offer/524860786372.html"},{"company_name":"深圳佰晟泰科技有限公司","image_url":"//cbu01.alicdn.com/img/ibank/2015/880/468/2649864088_207704770.summ.jpg","name":"厂家直销 四排尖钉狗链霸气野性宠物项圈 宠物用品 狗项圈","price":26.0,"url":"https://detail.1688.com/offer/524858994204.html"},{"company_name":"深圳佰晟泰科技有限公司","image_url":"//cbu01.alicdn.com/img/ibank/2015/829/862/2651268928_207704770.summ.jpg","name":"厂家直销狗项圈 加宽6颗狼牙尖钉宠物项圈 彪悍结实狗链 狗项圈","price":26.0,"url":"https://detail.1688.com/offer/524851527234.html"},{"company_name":"深圳佰晟泰科技有限公司","image_url":"//cbu01.alicdn.com/img/ibank/2015/764/961/2645169467_207704770.summ.jpg","name":"厂家直销宠物用品多功能宠物响片 狗哨 训狗器 止吠器 犬笛训狗器","price":2.8,"url":"https://detail.1688.com/offer/524805852006.html"},{"company_name":"深圳佰晟泰科技有限公司","image_url":"//cbu01.alicdn.com/img/ibank/2015/133/748/2640847331_207704770.summ.jpg","name":"自动止吠器 电击震动止吠器 宠物训练器 电子训狗器BT-6","price":45.0,"url":"https://detail.1688.com/offer/524793545607.html"},{"company_name":"深圳佰晟泰科技有限公司","image_url":"//cbu01.alicdn.com/img/ibank/2015/420/998/2644899024_207704770.summ.jpg","name":"厂家直销可调声控止吠器 训狗器 超声波自动止吠器 宠物用品BS-8","price":19.0,"url":"https://detail.1688.com/offer/524791537355.html"},{"company_name":"深圳佰晟泰科技有限公司","image_url":"//cbu01.alicdn.com/img/ibank/2015/633/691/2640196336_207704770.summ.jpg","name":"厂家直销训狗器 宠物训练器 狗项圈 猎狗蜂鸣器 超声波自动止吠器","price":140.0,"url":"https://detail.1688.com/offer/524786946111.html"},{"company_name":"深圳佰晟泰科技有限公司","image_url":"//cbu01.alicdn.com/img/ibank/2015/309/280/2640082903_207704770.summ.jpg","name":"声控电击止吠器 自动止吠器 超声波止吠器 电子训狗器X888","price":83.0,"url":"https://detail.1688.com/offer/524786469240.html"},{"company_name":"深圳佰晟泰科技有限公司","image_url":"//cbu01.alicdn.com/img/ibank/2015/231/508/2640805132_207704770.summ.jpg","name":"自动训狗器 训狗器 超声波止吠 宠物电击狗脖套 自动止吠器BT-1","price":18.0,"url":"https://detail.1688.com/offer/524758651951.html"},{"company_name":"深圳佰晟泰科技有限公司","image_url":"//cbu01.alicdn.com/img/ibank/2015/021/512/2633215120_207704770.summ.jpg","name":"厂家直销宠物狗升级版止吠器 自动止吠器 电击声控止吠器BK209","price":22.0,"url":"https://detail.1688.com/offer/524685652131.html"},{"company_name":"深圳佰晟泰科技有限公司","image_url":"//cbu01.alicdn.com/img/ibank/2015/208/593/2630395802_207704770.summ.jpg","name":"遥控震动止吠器 遥控训狗器 电子训狗器 远距离控制训狗器154","price":44.0,"url":"https://detail.1688.com/offer/524647928547.html"},{"company_name":"深圳佰晟泰科技有限公司","image_url":"//cbu01.alicdn.com/img/ibank/2015/972/832/2705238279_207704770.summ.jpg","name":"厂家直销宠物用品训练器 训狗器 止吠器 遥控训狗器018","price":160.0,"url":"https://detail.1688.com/offer/524637907974.html"},{"company_name":"深圳佰晟泰科技有限公司","image_url":"//cbu01.alicdn.com/img/ibank/2015/259/085/2666580952_207704770.summ.jpg","name":"爆款 12LED紫光手电筒 UV紫光手电筒 UV手电筒 厂家直销","price":6.0,"url":"https://detail.1688.com/offer/525222942035.html"},{"company_name":"深圳佰晟泰科技有限公司","image_url":"//cbu01.alicdn.com/img/ibank/2015/458/963/2676369854_207704770.summ.jpg","name":"UV紫光手电筒 UV紫光灯 铝合金电筒 验钞手电筒 9LED紫光电筒","price":4.8,"url":"https://detail.1688.com/offer/525258619021.html"},{"company_name":"深圳佰晟泰科技有限公司","image_url":"//cbu01.alicdn.com/img/ibank/2015/089/058/2671850980_207704770.summ.jpg","name":"现货UV手电筒 21LED紫光手电筒 UV验钞灯 紫光LED手电筒 紫光电筒","price":9.5,"url":"https://detail.1688.com/offer/525223623183.html"},{"company_name":"深圳佰晟泰科技有限公司","image_url":"//cbu01.alicdn.com/img/ibank/2015/475/933/2662339574_207704770.summ.jpg","name":"9LED便携紫光验钞灯手电筒 UV手电筒 UV紫光手电筒 新品批发","price":4.8,"url":"https://detail.1688.com/offer/525138877384.html"},{"company_name":"深圳佰晟泰科技有限公司","image_url":"//cbu01.alicdn.com/img/ibank/2015/036/371/2625173630_207704770.summ.jpg","name":"厂家直销 21led紫光手电筒 UV手电筒 多功能验钞紫外线手电筒","price":9.5,"url":"https://detail.1688.com/offer/524542737533.html"},{"company_name":"深圳佰晟泰科技有限公司","image_url":"//cbu01.alicdn.com/img/ibank/2015/259/085/2666580952_207704770.summ.jpg","name":"爆款手电筒12LED紫光手电筒 UV手电筒 12led紫外线手电筒 蝎子灯","price":6.0,"url":"https://detail.1688.com/offer/525138893064.html"},{"company_name":"深圳佰晟泰科技有限公司","image_url":"//cbu01.alicdn.com/img/ibank/2015/818/439/2657934818_207704770.summ.jpg","name":"厂家直销UV紫光电筒 9LED紫光手电筒 UV多功能验钞手电筒","price":4.8,"url":"https://detail.1688.com/offer/525012780490.html"},{"company_name":"深圳佰晟泰科技有限公司","image_url":"//cbu01.alicdn.com/img/ibank/2015/444/432/2629234444_207704770.summ.jpg","name":"UV紫光手电筒 UV紫光灯 铝合金电筒 验钞手电筒 21LED紫光电筒","price":9.5,"url":"https://detail.1688.com/offer/524627249324.html"},{"company_name":"深圳佰晟泰科技有限公司","image_url":"//cbu01.alicdn.com/img/ibank/2015/361/730/2646037163_207704770.summ.jpg","name":"厂家直销 四排尖钉狗链 霸气宠物项圈 宠物用品狗圈 狗狗项圈","price":25.0,"url":"https://detail.1688.com/offer/524860786372.html"},{"company_name":"深圳佰晟泰科技有限公司","image_url":"//cbu01.alicdn.com/img/ibank/2015/133/748/2640847331_207704770.summ.jpg","name":"自动止吠器 电击震动止吠器 宠物训练器 电子训狗器BT-6","price":45.0,"url":"https://detail.1688.com/offer/524793545607.html"},{"company_name":"深圳佰晟泰科技有限公司","image_url":"//cbu01.alicdn.com/img/ibank/2015/633/691/2640196336_207704770.summ.jpg","name":"厂家直销训狗器 宠物训练器 狗项圈 猎狗蜂鸣器 超声波自动止吠器","price":140.0,"url":"https://detail.1688.com/offer/524786946111.html"},{"company_name":"深圳佰晟泰科技有限公司","image_url":"//cbu01.alicdn.com/img/ibank/2015/346/192/2642291643_207704770.summ.jpg","name":"新款超声波止吠器 防狗止叫器 室外防水止吠器 电子止吠器","price":65.0,"url":"https://detail.1688.com/offer/524785582796.html"},{"company_name":"深圳佰晟泰科技有限公司","image_url":"//cbu01.alicdn.com/img/ibank/2015/309/280/2640082903_207704770.summ.jpg","name":"声控电击止吠器 自动止吠器 超声波止吠器 电子训狗器X888","price":83.0,"url":"https://detail.1688.com/offer/524786469240.html"},{"company_name":"深圳佰晟泰科技有限公司","image_url":"//cbu01.alicdn.com/img/ibank/2016/055/064/2870460550_207704770.summ.jpg","name":"声控电击自动止吠器 超声波止吠器  宠物训练器 训狗器PET-852","price":23.0,"url":"https://detail.1688.com/offer/524785534189.html"},{"company_name":"深圳佰晟泰科技有限公司","image_url":"//cbu01.alicdn.com/img/ibank/2015/972/832/2705238279_207704770.summ.jpg","name":"厂家直销宠物用品训练器 训狗器 止吠器 遥控训狗器018","price":160.0,"url":"https://detail.1688.com/offer/524637907974.html"},{"company_name":"深圳佰晟泰科技有限公司","image_url":"//cbu01.alicdn.com/img/ibank/2015/070/659/2634956070_207704770.summ.jpg","name":"最新款止吠器 高品质训狗器 自动止吠器 遥控训狗器 厂家直销008","price":120.0,"url":"https://detail.1688.com/offer/524669318662.html"},{"company_name":"深圳佰晟泰科技有限公司","image_url":"//cbu01.alicdn.com/img/ibank/2015/444/432/2629234444_207704770.summ.jpg","name":"UV紫光手电筒 UV紫光灯 铝合金电筒 验钞手电筒 21LED紫光电筒","price":9.5,"url":"https://detail.1688.com/offer/524627249324.html"},{"company_name":"深圳佰晟泰科技有限公司","image_url":"//cbu01.alicdn.com/img/ibank/2015/301/255/2631552103_207704770.summ.jpg","name":"厂家直销可调节超声波犬笛 训狗器 宠物狗哨  犬笛训练 狗哨子","price":3.0,"url":"https://detail.1688.com/offer/524609824629.html"},{"company_name":"深圳佰晟泰科技有限公司","image_url":"//cbu01.alicdn.com/img/ibank/2015/645/714/2623417546_207704770.summ.jpg","name":"热销款电子训狗器 止吠器 防水可充电宠物训练器 遥控训狗器613","price":100.0,"url":"https://detail.1688.com/offer/524340067476.html"},{"company_name":"深圳佰晟泰科技有限公司","image_url":"//cbu01.alicdn.com/img/ibank/2016/496/493/2713394694_207704770.summ.jpg","name":"厂家直销遥控训狗器 止吠器 宠物用 电击震动声音训狗器998C","price":44.0,"url":"https://detail.1688.com/offer/525963226131.html"},{"company_name":"深圳佰晟泰科技有限公司","image_url":"//cbu01.alicdn.com/img/ibank/2016/333/488/2886884333_207704770.summ.jpg","name":"1000米充电防水遥控训狗器 止吠器 电击震动训狗器 宠物用品613","price":115.0,"url":"https://detail.1688.com/offer/529033058791.html"},{"company_name":"深圳佰晟泰科技有限公司","image_url":"//cbu01.alicdn.com/img/ibank/2015/070/659/2634956070_207704770.summ.jpg","name":"最新款止吠器 高品质训狗器 自动止吠器 遥控训狗器 厂家直销008","price":120.0,"url":"https://detail.1688.com/offer/524669318662.html"},{"company_name":"深圳佰晟泰科技有限公司","image_url":"//cbu01.alicdn.com/img/ibank/2016/069/239/3044932960_207704770.summ.jpg","name":"全新热销训狗器 止吠器 4合一功能高端训练器","price":145.0,"url":"https://detail.1688.com/offer/531882369540.html"},{"company_name":"深圳佰晟泰科技有限公司","image_url":"//cbu01.alicdn.com/img/ibank/2015/972/832/2705238279_207704770.summ.jpg","name":"厂家直销宠物用品训练器 训狗器 止吠器 遥控训狗器018","price":160.0,"url":"https://detail.1688.com/offer/524637907974.html"},{"company_name":"深圳佰晟泰科技有限公司","image_url":"//cbu01.alicdn.com/img/ibank/2015/208/593/2630395802_207704770.summ.jpg","name":"遥控震动止吠器 遥控训狗器 电子训狗器 远距离控制训狗器154","price":44.0,"url":"https://detail.1688.com/offer/524647928547.html"},{"company_name":"深圳佰晟泰科技有限公司","image_url":"//cbu01.alicdn.com/img/ibank/2016/049/325/3047523940_207704770.summ.jpg","name":"新款狗狗止吠器 遥控训狗器 自动止吠器 宠物用品PTS610 训狗器","price":175.0,"url":"https://detail.1688.com/offer/531883505757.html"},{"company_name":"深圳佰晟泰科技有限公司","image_url":"//cbu01.alicdn.com/img/ibank/2015/136/310/2648013631_207704770.summ.jpg","name":"户外打猎声音追踪器 遥控电子训狗器 电击震动蜂鸣器 止吠器","price":340.0,"url":"https://detail.1688.com/offer/524831949080.html"},{"company_name":"深圳佰晟泰科技有限公司","image_url":"//cbu01.alicdn.com/img/ibank/2016/611/461/3637164116_207704770.summ.jpg","name":"新款遥控训狗器 充电防水止吠器 电击震动训狗 器项圈","price":78.0,"url":"https://detail.1688.com/offer/541771675604.html"},{"company_name":"深圳佰晟泰科技有限公司","image_url":"//cbu01.alicdn.com/img/ibank/2016/596/364/2870463695_207704770.summ.jpg","name":"一拖三无线 遥控训狗器 宠物训练器 电子训狗器 自动止吠器032","price":85.0,"url":"https://detail.1688.com/offer/524610060093.html"},{"company_name":"深圳佰晟泰科技有限公司","image_url":"//cbu01.alicdn.com/img/ibank/2017/477/806/4563608774_207704770.summ.jpg","name":"2017新款潜水训狗器 蓝屏训狗器 止吠器 训犬器","price":210.0,"url":"https://detail.1688.com/offer/557147240517.html"},{"company_name":"深圳佰晟泰科技有限公司","image_url":"//cbu01.alicdn.com/img/ibank/2016/480/405/3115504084_207704770.summ.jpg","name":"2016年新款宠物无线电子围栏  宠物训练器 止吠器","price":235.0,"url":"https://detail.1688.com/offer/533662237121.html"},{"company_name":"深圳佰晟泰科技有限公司","image_url":"//cbu01.alicdn.com/img/ibank/2016/195/023/3268320591_207704770.summ.jpg","name":"新款 无线电子围栏 宠物用品 电子围栏充电防水 训狗器","price":150.0,"url":"https://detail.1688.com/offer/536222308536.html"},{"company_name":"深圳佰晟泰科技有限公司","image_url":"//cbu01.alicdn.com/img/ibank/2015/313/237/2657732313_207704770.summ.jpg","name":"宠物隔离静电毯 宠物静电毯 训练毯 训狗器 狗猫训练用品M2160","price":109.0,"url":"https://detail.1688.com/offer/525040260698.html"},{"company_name":"深圳佰晟泰科技有限公司","image_url":"//cbu01.alicdn.com/img/ibank/2016/477/070/3636070774_207704770.summ.jpg","name":"无线电子围栏 宠物电子围栏 500米半径 接收器不限 防水可充电","price":300.0,"url":"https://detail.1688.com/offer/541756777417.html"},{"company_name":"深圳佰晟泰科技有限公司","image_url":"//cbu01.alicdn.com/img/ibank/2017/194/301/4358103491_207704770.summ.jpg","name":"新款自动止吠器 遥控训狗器 二合一宠物无线围栏","price":180.0,"url":"https://detail.1688.com/offer/554015251049.html"},{"company_name":"深圳佰晟泰科技有限公司","image_url":"//cbu01.alicdn.com/img/ibank/2015/626/614/2625416626_207704770.summ.jpg","name":"室外超声波止吠器 室外超声波驱狗器 房子止吠器 训狗器","price":70.0,"url":"https://detail.1688.com/offer/524364699967.html"},{"company_name":"深圳佰晟泰科技有限公司","image_url":"//cbu01.alicdn.com/img/ibank/2015/746/298/2622892647_207704770.summ.jpg","name":"自动超声波可调节电击止吠器 训狗器 宠物用品 BK208","price":24.0,"url":"https://detail.1688.com/offer/524406524296.html"},{"company_name":"深圳佰晟泰科技有限公司","image_url":"//cbu01.alicdn.com/img/ibank/2015/645/714/2623417546_207704770.summ.jpg","name":"热销款电子训狗器 止吠器 防水可充电宠物训练器 遥控训狗器613","price":100.0,"url":"https://detail.1688.com/offer/524340067476.html"}]}