{"products":[{"company_name":"广州市卡绿美汽车用品有限公司","image_url":"//cbu01.alicdn.com/img/ibank/2016/657/492/3202294756_2128240986.search.jpg","name":"跨境专供得然福汽车座椅缝隙置物盒收纳箱车载多功能储物箱皮革","price":36.0,"url":"https://detail.1688.com/offer/534908499886.html"},{"company_name":"广州市卡绿美汽车用品有限公司","image_url":"//cbu01.alicdn.com/img/ibank/2017/103/838/7292838301_2128240986.search.jpg","name":"跨境专供车载USB带充电收纳盒多功能夹缝水杯架汽车零钱盒储物盒","price":45.0,"url":"https://detail.1688.com/offer/44316350086.html"},{"company_name":"广州市卡绿美汽车用品有限公司","image_url":"//cbu01.alicdn.com/img/ibank/2017/004/819/4468918400_2128240986.search.jpg","name":"跨境专供得然福车载多功能储物盒汽车座椅缝隙置物盒垃圾桶夹缝","price":30.0,"url":"https://detail.1688.com/offer/535009717001.html"},{"company_name":"广州市卡绿美汽车用品有限公司","image_url":"//cbu01.alicdn.com/img/ibank/2018/684/320/8408023486_2128240986.search.jpg","name":"跨境专供汽车座椅多功能置物盒车载挂式储物椅背收纳袋","price":30.0,"url":"https://detail.1688.com/offer/524103671986.html"},{"company_name":"广州市卡绿美汽车用品有限公司","image_url":"//cbu01.alicdn.com/img/ibank/2017/162/483/4581384261_2128240986.search.jpg","name":"跨境专供英文绒脚车载多功能储物盒汽车零钱盒座椅缝隙置物盒收纳","price":30.0,"url":"https://detail.1688.com/offer/534975730985.html"},{"company_name":"广州市卡绿美汽车用品有限公司","image_url":"//cbu01.alicdn.com/img/ibank/2018/609/768/8659867906_2128240986.search.jpg","name":"得然福车载多功能水杯架收纳盒名片水杯架包皮储物盒置物盒","price":23.0,"url":"https://detail.1688.com/offer/551156968769.html"},{"company_name":"广州市卡绿美汽车用品有限公司","image_url":"//cbu01.alicdn.com/img/ibank/2018/162/597/8108795261_2128240986.search.jpg","name":"跨境专供得然福车载多功能水杯架收纳盒水杯架包皮储物盒置物盒","price":26.0,"url":"https://detail.1688.com/offer/564252763778.html"},{"company_name":"广州市卡绿美汽车用品有限公司","image_url":"//cbu01.alicdn.com/img/ibank/2018/461/581/8693185164_2128240986.search.jpg","name":"跨境电商得然福厂家车载多功能储物盒汽车座椅缝隙置物垃圾桶夹缝","price":8.0,"url":"https://detail.1688.com/offer/527323752557.html"},{"company_name":"广州市卡绿美汽车用品有限公司","image_url":"//cbu01.alicdn.com/img/ibank/2017/128/365/4177563821_2128240986.search.jpg","name":"跨境专供汽车纸巾盒多功能纸巾抽车载遮阳挡椅背多功能收纳盒纸抽","price":15.0,"url":"https://detail.1688.com/offer/524173336535.html"},{"company_name":"广州市卡绿美汽车用品有限公司","image_url":"//cbu01.alicdn.com/img/ibank/2018/125/053/8745350521_2128240986.search.jpg","name":"汽车用品车上抽纸盒挂式天窗创意车载纸巾盒挂遮阳板车载卡片夹","price":30.0,"url":"https://detail.1688.com/offer/567593600780.html"},{"company_name":"广州市卡绿美汽车用品有限公司","image_url":"//cbu01.alicdn.com/img/ibank/2017/419/380/4163083914_2128240986.search.jpg","name":"跨境专供得然福荔枝纹木制纸巾盒汽车可夹天窗/遮阳挡门侧/椅背","price":20.0,"url":"https://detail.1688.com/offer/533801881756.html"},{"company_name":"广州市卡绿美汽车用品有限公司","image_url":"//cbu01.alicdn.com/img/ibank/2018/809/191/8593191908_2128240986.search.jpg","name":"跨境专供得然福车载临时停车纸巾包多功能创意名片夹收纳夹","price":32.0,"url":"https://detail.1688.com/offer/566034835930.html"},{"company_name":"广州市卡绿美汽车用品有限公司","image_url":"//cbu01.alicdn.com/img/ibank/2018/457/417/8556714754_2128240986.search.jpg","name":"汽车车载扶手箱纸巾盒多功能创意抽纸盒座式停车牌抽纸盒餐巾收纳","price":35.0,"url":"https://detail.1688.com/offer/565270696228.html"},{"company_name":"广州市卡绿美汽车用品有限公司","image_url":"//cbu01.alicdn.com/img/ibank/2018/136/368/8598863631_2128240986.search.jpg","name":"跨境专供得然福汽车纸巾包遮阳板小羊皮车载纸巾盒纸巾套抽纸盒","price":15.0,"url":"https://detail.1688.com/offer/562335511750.html"},{"company_name":"广州市卡绿美汽车用品有限公司","image_url":"//cbu01.alicdn.com/img/ibank/2016/670/870/3162078076_2128240986.search.jpg","name":"跨境专供得然福汽车纸巾包遮阳板椅背挂式车载纸巾盒纸巾套抽纸盒","price":19.0,"url":"https://detail.1688.com/offer/534245859077.html"},{"company_name":"广州市卡绿美汽车用品有限公司","image_url":"//cbu01.alicdn.com/img/ibank/2017/694/645/4119546496_2128240986.search.jpg","name":"得然福创意新品汽车用品创意椭圆形小羊纹车载logo纸巾盒车用座式","price":27.0,"url":"https://detail.1688.com/offer/549230381753.html"},{"company_name":"广州市卡绿美汽车用品有限公司","image_url":"//cbu01.alicdn.com/img/ibank/2017/500/972/4416279005_2128240986.search.jpg","name":"得然福车载出风口挂饰手机袋杂物兜收纳袋多功能置物兜","price":8.0,"url":"https://detail.1688.com/offer/554933072576.html"},{"company_name":"广州市卡绿美汽车用品有限公司","image_url":"//cbu01.alicdn.com/img/ibank/2016/182/066/3164660281_2128240986.search.jpg","name":"得然福车载汽车夜光储物盒置物袋多功能收纳袋汽车内饰用品","price":6.0,"url":"https://detail.1688.com/offer/534439465082.html"},{"company_name":"广州市卡绿美汽车用品有限公司","image_url":"//cbu01.alicdn.com/img/ibank/2018/458/340/8655043854_2128240986.search.jpg","name":"得然福荔枝纹带标手机袋汽车出风口杂物桶收纳袋汽车汽车用品","price":8.5,"url":"https://detail.1688.com/offer/525788057010.html"},{"company_name":"广州市卡绿美汽车用品有限公司","image_url":"//cbu01.alicdn.com/img/ibank/2018/021/777/8662777120_2128240986.search.jpg","name":"得然福小羊皮斜圆杂物桶手机收纳袋创意车载出风口挂袋汽车手机袋","price":8.0,"url":"https://detail.1688.com/offer/45771541369.html"},{"company_name":"广州市卡绿美汽车用品有限公司","image_url":"//cbu01.alicdn.com/img/ibank/2017/019/248/4376842910_2128240986.search.jpg","name":"得然福小羊皮汽车出风口手机袋风口置物袋车用收纳盒多功能杂物盒","price":3.0,"url":"https://detail.1688.com/offer/45157054718.html"},{"company_name":"广州市卡绿美汽车用品有限公司","image_url":"//cbu01.alicdn.com/img/ibank/2017/012/171/4547171210_2128240986.search.jpg","name":"得然福车载汽车储物盒置物袋多功能收纳袋汽车手机袋卡片盒收纳盒","price":9.5,"url":"https://detail.1688.com/offer/40484559007.html"},{"company_name":"广州市卡绿美汽车用品有限公司","image_url":"//cbu01.alicdn.com/img/ibank/2018/684/320/8408023486_2128240986.search.jpg","name":"跨境专供汽车座椅多功能置物盒车载挂式储物椅背收纳袋","price":30.0,"url":"https://detail.1688.com/offer/524103671986.html"},{"company_name":"广州市卡绿美汽车用品有限公司","image_url":"//cbu01.alicdn.com/img/ibank/2018/461/581/8693185164_2128240986.search.jpg","name":"跨境电商得然福厂家车载多功能储物盒汽车座椅缝隙置物垃圾桶夹缝","price":8.0,"url":"https://detail.1688.com/offer/527323752557.html"},{"company_name":"广州市卡绿美汽车用品有限公司","image_url":"//cbu01.alicdn.com/img/ibank/2015/062/007/2673700260_2128240986.search.jpg","name":"跨境专供得然福汽车遮阳板CD夹小羊皮折角CD板汽车cd包碟包光盘套","price":13.0,"url":"https://detail.1688.com/offer/43168801842.html"},{"company_name":"广州市卡绿美汽车用品有限公司","image_url":"//cbu01.alicdn.com/img/ibank/2017/483/526/4155625384_2128240986.search.jpg","name":"跨境专供得然福汽车荔枝纹三合一CD板纸巾包纸巾盒纸巾抽遮阳板","price":22.0,"url":"https://detail.1688.com/offer/528688094052.html"},{"company_name":"广州市卡绿美汽车用品有限公司","image_url":"//cbu01.alicdn.com/img/ibank/2018/268/995/8719599862_2128240986.search.jpg","name":"得然福小羊皮驾驶本CD板 小羊皮CD板 多功能创意CD板","price":14.0,"url":"https://detail.1688.com/offer/45689271057.html"},{"company_name":"广州市卡绿美汽车用品有限公司","image_url":"//cbu01.alicdn.com/img/ibank/2018/693/077/8719770396_2128240986.search.jpg","name":"得然福汽车CD夹套多功能车用光盘碟片收纳袋车载CD包CD袋汽车用品","price":7.5,"url":"https://detail.1688.com/offer/538638123744.html"},{"company_name":"广州市卡绿美汽车用品有限公司","image_url":"//cbu01.alicdn.com/img/ibank/2017/224/423/8005324422_2128240986.search.jpg","name":"跨境专供得然福多功能卡片名片夹车载CD收纳盒汽车光盘碟包眼镜夹","price":17.0,"url":"https://detail.1688.com/offer/563452853345.html"},{"company_name":"广州市卡绿美汽车用品有限公司","image_url":"//cbu01.alicdn.com/img/ibank/2017/158/746/4471647851_2128240986.search.jpg","name":"跨境专供得然福功能纸巾套车载车用电话牌遮阳板挂式抽纸盒纸巾包","price":40.0,"url":"https://detail.1688.com/offer/534975918944.html"},{"company_name":"广州市卡绿美汽车用品有限公司","image_url":"//cbu01.alicdn.com/img/ibank/2018/478/158/8754851874_2128240986.search.jpg","name":"得然福汽车皮革多功能CD包车载遮阳板CD夹 眼镜夹卡片名片夹","price":14.0,"url":"https://detail.1688.com/offer/524509893270.html"},{"company_name":"广州市卡绿美汽车用品有限公司","image_url":"//cbu01.alicdn.com/img/ibank/2018/983/901/8739109389_2128240986.search.jpg","name":"得然福汽车CD夹  牛皮CD夹 车用多功能 遮阳板CD夹","price":13.0,"url":"https://detail.1688.com/offer/40450824542.html"},{"company_name":"广州市卡绿美汽车用品有限公司","image_url":"//cbu01.alicdn.com/img/ibank/2017/459/186/4158681954_2128240986.search.jpg","name":"跨境专供得然福小羊纹汽车车载皮质后备箱折叠多功能储物箱置物盒","price":45.0,"url":"https://detail.1688.com/offer/541047208578.html"},{"company_name":"广州市卡绿美汽车用品有限公司","image_url":"//cbu01.alicdn.com/img/ibank/2018/684/320/8408023486_2128240986.search.jpg","name":"跨境专供汽车座椅多功能置物盒车载挂式储物椅背收纳袋","price":30.0,"url":"https://detail.1688.com/offer/524103671986.html"},{"company_name":"广州市卡绿美汽车用品有限公司","image_url":"//cbu01.alicdn.com/img/ibank/2014/140/724/1851427041_2128240986.search.jpg","name":"得然福新款红酒大号车载礼品储物箱 折叠储物箱后备箱整理箱 折叠","price":70.0,"url":"https://detail.1688.com/offer/38518295539.html"},{"company_name":"广州市卡绿美汽车用品有限公司","image_url":"//cbu01.alicdn.com/img/ibank/2016/467/208/3147802764_2128240986.search.jpg","name":"得然福条纹杂物箱汽车收纳箱储物箱汽车后备箱整理箱盒袋车载杂物","price":75.0,"url":"https://detail.1688.com/offer/534166982384.html"},{"company_name":"广州市卡绿美汽车用品有限公司","image_url":"//cbu01.alicdn.com/img/ibank/2016/071/605/3749506170_2128240986.search.jpg","name":"得然福横条大号汽车储物箱车载收纳箱用品整理盒杂物盒多功能折叠","price":80.0,"url":"https://detail.1688.com/offer/543645829402.html"},{"company_name":"广州市卡绿美汽车用品有限公司","image_url":"//cbu01.alicdn.com/img/ibank/2016/462/804/3749408264_2128240986.search.jpg","name":"得然福横条小号后备箱储物箱 车载收纳箱整理盒杂物盒多功能折叠","price":70.0,"url":"https://detail.1688.com/offer/543644621815.html"},{"company_name":"广州市卡绿美汽车用品有限公司","image_url":"//cbu01.alicdn.com/img/ibank/2014/900/526/1852625009_2128240986.search.jpg","name":"得然福新款折叠式经典多星汽车后备箱储物置物箱家车两用收纳整理","price":75.0,"url":"https://detail.1688.com/offer/40102812617.html"},{"company_name":"广州市卡绿美汽车用品有限公司","image_url":"//cbu01.alicdn.com/img/ibank/2014/511/136/1852631115_2128240986.search.jpg","name":"厂家供应新款折叠式汽车后备箱储物盒置物家用车用收纳整理箱批发","price":75.0,"url":"https://detail.1688.com/offer/40072694137.html"},{"company_name":"广州市卡绿美汽车用品有限公司","image_url":"//cbu01.alicdn.com/img/ibank/2016/657/492/3202294756_2128240986.search.jpg","name":"跨境专供得然福汽车座椅缝隙置物盒收纳箱车载多功能储物箱皮革","price":36.0,"url":"https://detail.1688.com/offer/534908499886.html"},{"company_name":"广州市卡绿美汽车用品有限公司","image_url":"//cbu01.alicdn.com/img/ibank/2017/103/838/7292838301_2128240986.search.jpg","name":"跨境专供车载USB带充电收纳盒多功能夹缝水杯架汽车零钱盒储物盒","price":45.0,"url":"https://detail.1688.com/offer/44316350086.html"},{"company_name":"广州市卡绿美汽车用品有限公司","image_url":"//cbu01.alicdn.com/img/ibank/2017/162/483/4581384261_2128240986.search.jpg","name":"跨境专供英文绒脚车载多功能储物盒汽车零钱盒座椅缝隙置物盒收纳","price":30.0,"url":"https://detail.1688.com/offer/534975730985.html"},{"company_name":"广州市卡绿美汽车用品有限公司","image_url":"//cbu01.alicdn.com/img/ibank/2017/004/819/4468918400_2128240986.search.jpg","name":"跨境专供得然福车载多功能储物盒汽车座椅缝隙置物盒垃圾桶夹缝","price":30.0,"url":"https://detail.1688.com/offer/535009717001.html"},{"company_name":"广州市卡绿美汽车用品有限公司","image_url":"//cbu01.alicdn.com/img/ibank/2017/153/415/4373514351_2128240986.search.jpg","name":"得然福厂家车载多功能储物盒汽车座椅缝隙置物盒收纳盒夹缝","price":35.0,"url":"https://detail.1688.com/offer/552044558072.html"},{"company_name":"广州市卡绿美汽车用品有限公司","image_url":"//cbu01.alicdn.com/img/ibank/2018/609/768/8659867906_2128240986.search.jpg","name":"得然福车载多功能水杯架收纳盒名片水杯架包皮储物盒置物盒","price":23.0,"url":"https://detail.1688.com/offer/551156968769.html"},{"company_name":"广州市卡绿美汽车用品有限公司","image_url":"//cbu01.alicdn.com/img/ibank/2017/019/248/4376842910_2128240986.search.jpg","name":"得然福小羊皮汽车出风口手机袋风口置物袋车用收纳盒多功能杂物盒","price":3.0,"url":"https://detail.1688.com/offer/45157054718.html"},{"company_name":"广州市卡绿美汽车用品有限公司","image_url":"//cbu01.alicdn.com/img/ibank/2017/483/526/4155625384_2128240986.search.jpg","name":"跨境专供得然福汽车荔枝纹三合一CD板纸巾包纸巾盒纸巾抽遮阳板","price":22.0,"url":"https://detail.1688.com/offer/528688094052.html"},{"company_name":"广州市卡绿美汽车用品有限公司","image_url":"//cbu01.alicdn.com/img/ibank/2018/125/053/8745350521_2128240986.summ.jpg","name":"汽车用品车上抽纸盒挂式天窗创意车载纸巾盒挂遮阳板车载卡片夹","price":30.0,"url":"https://detail.1688.com/offer/567593600780.html"},{"company_name":"广州市卡绿美汽车用品有限公司","image_url":"//cbu01.alicdn.com/img/ibank/2017/428/693/7094396824_2128240986.summ.jpg","name":"跨境专供汽车座椅收纳袋挂袋车用椅背置物袋多功能车载储物收纳箱","price":18.0,"url":"https://detail.1688.com/offer/561905213637.html"},{"company_name":"广州市卡绿美汽车用品有限公司","image_url":"//cbu01.alicdn.com/img/ibank/2017/041/938/7005839140_2128240986.summ.jpg","name":"跨境专供汽车夹缝车载水杯架多功能置物车内用品座椅缝隙储物盒","price":11.0,"url":"https://detail.1688.com/offer/561868473757.html"},{"company_name":"广州市卡绿美汽车用品有限公司","image_url":"//cbu01.alicdn.com/img/ibank/2018/162/597/8108795261_2128240986.summ.jpg","name":"跨境专供得然福车载多功能水杯架收纳盒水杯架包皮储物盒置物盒","price":26.0,"url":"https://detail.1688.com/offer/564252763778.html"},{"company_name":"广州市卡绿美汽车用品有限公司","image_url":"//cbu01.alicdn.com/img/ibank/2017/224/423/8005324422_2128240986.summ.jpg","name":"跨境专供得然福多功能卡片名片夹车载CD收纳盒汽车光盘碟包眼镜夹","price":17.0,"url":"https://detail.1688.com/offer/563452853345.html"},{"company_name":"广州市卡绿美汽车用品有限公司","image_url":"//cbu01.alicdn.com/img/ibank/2018/609/768/8659867906_2128240986.summ.jpg","name":"得然福车载多功能水杯架收纳盒名片水杯架包皮储物盒置物盒","price":23.0,"url":"https://detail.1688.com/offer/551156968769.html"},{"company_name":"广州市卡绿美汽车用品有限公司","image_url":"//cbu01.alicdn.com/img/ibank/2016/462/804/3749408264_2128240986.summ.jpg","name":"得然福横条小号后备箱储物箱 车载收纳箱整理盒杂物盒多功能折叠","price":70.0,"url":"https://detail.1688.com/offer/543644621815.html"},{"company_name":"广州市卡绿美汽车用品有限公司","image_url":"//cbu01.alicdn.com/img/ibank/2017/281/760/4178067182_2128240986.summ.jpg","name":"得然福 车用牛皮车载置物盒汽车座椅缝隙塞储物盒汽车用品收纳袋","price":32.0,"url":"https://detail.1688.com/offer/543128243783.html"}]}