{"products":[{"company_name":"南宫市浪淘沙皮毛厂","image_url":"//cbu01.alicdn.com/img/ibank/2016/207/872/3667278702_118073014.220x220.jpg","name":"汽车坐垫用品厂家冬季加热纯羊毛皮毛一体毛绒单片座垫套小三件套","price":30.6,"url":"https://detail.1688.com/offer/1298968180.html"},{"company_name":"南宫市浪淘沙皮毛厂","image_url":"//cbu01.alicdn.com/img/ibank/2017/212/025/7271520212_118073014.220x220.jpg","name":"汽车坐垫用品冬季加热羊毛羊绒靠背皮毛一体三件套单个厂家直销","price":189.3,"url":"https://detail.1688.com/offer/560096674639.html"},{"company_name":"南宫市浪淘沙皮毛厂","image_url":"//cbu01.alicdn.com/img/ibank/2016/207/872/3667278702_118073014.220x220.jpg","name":"汽车羊毛坐垫 小三件套 单个坐垫汽车坐垫冬季沙发垫批发定做包邮","price":280.0,"url":"https://detail.1688.com/offer/35308726692.html"},{"company_name":"南宫市浪淘沙皮毛厂","image_url":"//cbu01.alicdn.com/img/ibank/2017/212/025/7271520212_118073014.220x220.jpg","name":"汽车用品冬季新款毛绒座垫羊毛汽车坐垫冬季坐垫迈腾b8一件代发","price":189.3,"url":"https://detail.1688.com/offer/559943800139.html"},{"company_name":"南宫市浪淘沙皮毛厂","image_url":"//cbu01.alicdn.com/img/ibank/2014/861/249/1609942168_118073014.220x220.jpg","name":"冬季新款座垫 小三件汽车坐垫 冬季羊毛三件套棉垫 简约车垫","price":27.9,"url":"https://detail.1688.com/offer/35610060946.html"},{"company_name":"南宫市浪淘沙皮毛厂","image_url":"//cbu01.alicdn.com/img/ibank/2016/742/322/3748223247_118073014.220x220.jpg","name":"汽车坐垫用品冬季迈腾b8羊毛坐垫座垫厂家靠背一件代发专车专用","price":385.05,"url":"https://detail.1688.com/offer/1286253567.html"},{"company_name":"南宫市浪淘沙皮毛厂","image_url":"//cbu01.alicdn.com/img/ibank/2017/016/218/4934812610_118073014.220x220.jpg","name":"批发新款汽车羊毛坐垫澳毛皮毛一体座垫皮草汽车靠背特价车垫","price":380.0,"url":"https://detail.1688.com/offer/559661359166.html"},{"company_name":"南宫市浪淘沙皮毛厂","image_url":"//cbu01.alicdn.com/img/ibank/2018/436/865/8543568634_118073014.220x220.jpg","name":"汽车坐垫无靠羊毛毛绒小三件套厂家批发冬季新款加热","price":80.4,"url":"https://detail.1688.com/offer/562121515260.html"},{"company_name":"南宫市浪淘沙皮毛厂","image_url":"//cbu01.alicdn.com/img/ibank/2016/207/872/3667278702_118073014.220x220.jpg","name":"浪淘沙 羊毛坐垫 汽车坐垫 座垫厂家直销 100%羊毛","price":30.6,"url":"https://detail.1688.com/offer/541653065879.html"},{"company_name":"南宫市浪淘沙皮毛厂","image_url":"//cbu01.alicdn.com/img/ibank/2016/800/200/3607002008_118073014.220x220.jpg","name":"浪淘沙羊剪绒羊毛坐垫座垫短毛小三件厂家直销批发丰田大众现代","price":30.75,"url":"https://detail.1688.com/offer/528393612462.html"},{"company_name":"南宫市浪淘沙皮毛厂","image_url":"//cbu01.alicdn.com/img/ibank/2017/326/685/4933586623_118073014.220x220.jpg","name":"毛绒椅子垫冬季加厚防滑老板椅垫圆形学生凳子垫电脑餐椅家用坐垫","price":9.02,"url":"https://detail.1688.com/offer/559444860847.html"},{"company_name":"南宫市浪淘沙皮毛厂","image_url":"//cbu01.alicdn.com/img/ibank/2017/523/087/5351780325_118073014.220x220.jpg","name":"汽车坐垫 羊毛坐垫 冬季汽车座垫皮毛一体羊皮坐垫毛垫","price":385.05,"url":"https://detail.1688.com/offer/542267077147.html"},{"company_name":"南宫市浪淘沙皮毛厂","image_url":"//cbu01.alicdn.com/img/ibank/2018/184/659/8090956481_118073014.220x220.jpg","name":"2017新款荞麦壳汽车坐垫四季通用可定制秋季汽车座垫用品一件代发","price":287.52,"url":"https://detail.1688.com/offer/563788459662.html"},{"company_name":"南宫市浪淘沙皮毛厂","image_url":"//cbu01.alicdn.com/img/ibank/2018/065/439/8052934560_118073014.220x220.jpg","name":"2017新款四季通用荞麦壳汽车座垫 秋季汽车座垫 丝绒两面汽车坐垫","price":151.0,"url":"https://detail.1688.com/offer/563619014860.html"},{"company_name":"南宫市浪淘沙皮毛厂","image_url":"//cbu01.alicdn.com/img/ibank/2017/955/008/4934800559_118073014.220x220.jpg","name":"批发新款汽车羊毛坐垫澳毛皮毛一体座垫皮草汽车靠背特价车垫","price":380.0,"url":"https://detail.1688.com/offer/562880367446.html"},{"company_name":"南宫市浪淘沙皮毛厂","image_url":"//cbu01.alicdn.com/img/ibank/2016/742/322/3748223247_118073014.220x220.jpg","name":"汽车坐垫用品冬季迈腾b8羊毛坐垫座垫厂家靠背一件代发专车专用","price":385.05,"url":"https://detail.1688.com/offer/1286253567.html"},{"company_name":"南宫市浪淘沙皮毛厂","image_url":"//cbu01.alicdn.com/img/ibank/2013/837/128/946821738_118073014.search.jpg","name":"羊毛把套 冬季 方向盘套 新款羊毛把套 汽车方向盘套 厂家批发","price":6.8,"url":"https://detail.1688.com/offer/1282791892.html"},{"company_name":"南宫市浪淘沙皮毛厂","image_url":"//cbu01.alicdn.com/img/ibank/2013/192/076/980670291_118073014.search.jpg","name":"浪淘沙 把套 羊毛方向盘套 新款羊毛把套 汽车方向盘套厂家批发","price":39.0,"url":"https://detail.1688.com/offer/1282037957.html"},{"company_name":"南宫市浪淘沙皮毛厂","image_url":"//cbu01.alicdn.com/img/ibank/2013/418/380/986083814_118073014.search.jpg","name":"浪淘沙 把套 方向盘套冬汽车把套 羊毛方向盘套一件代发厂家直销","price":40.0,"url":"https://detail.1688.com/offer/1293170031.html"},{"company_name":"南宫市浪淘沙皮毛厂","image_url":"//cbu01.alicdn.com/img/ibank/2017/091/564/7815465190_118073014.220x220.jpg","name":"吉利新帝豪EC715车衣EC718车罩盖车布防晒防雨防尘隔热专用车外套","price":52.0,"url":"https://detail.1688.com/offer/563840466126.html"},{"company_name":"南宫市浪淘沙皮毛厂","image_url":"//cbu01.alicdn.com/img/ibank/2017/091/564/7815465190_118073014.220x220.jpg","name":"福特新经典福克斯两厢福睿斯三厢专用防晒隔热防雨遮阳汽车车衣罩","price":52.0,"url":"https://detail.1688.com/offer/563833770744.html"},{"company_name":"南宫市浪淘沙皮毛厂","image_url":"//cbu01.alicdn.com/img/ibank/2017/091/564/7815465190_118073014.220x220.jpg","name":"东风风神新A60A30 S30 H30 AX7 AX3专用车衣车罩防晒防雨隔热外套","price":52.0,"url":"https://detail.1688.com/offer/563917699340.html"},{"company_name":"南宫市浪淘沙皮毛厂","image_url":"//cbu01.alicdn.com/img/ibank/2017/091/564/7815465190_118073014.220x220.jpg","name":"新款铝膜广本雅阁九9代专用车衣防晒防雨本田雅阁8八代汽车罩外套","price":52.0,"url":"https://detail.1688.com/offer/563840054178.html"},{"company_name":"南宫市浪淘沙皮毛厂","image_url":"//cbu01.alicdn.com/img/ibank/2017/091/564/7815465190_118073014.220x220.jpg","name":"新款比亚迪戴姆勒腾势专用车衣车罩防雨防尘防晒遮阳隔热汽车外套","price":52.0,"url":"https://detail.1688.com/offer/563666504186.html"},{"company_name":"南宫市浪淘沙皮毛厂","image_url":"//cbu01.alicdn.com/img/ibank/2017/091/564/7815465190_118073014.220x220.jpg","name":"东风日产蓝鸟车衣车罩加厚16款尼桑蓝鸟专用防晒雨隔热遮阳汽车套","price":49.92,"url":"https://detail.1688.com/offer/563666504185.html"},{"company_name":"南宫市浪淘沙皮毛厂","image_url":"//cbu01.alicdn.com/img/ibank/2017/091/564/7815465190_118073014.220x220.jpg","name":"众泰云100车衣车罩专用加厚隔热防晒防雨防雪电动汽车遮阳雨衣","price":49.92,"url":"https://detail.1688.com/offer/563666564166.html"},{"company_name":"南宫市浪淘沙皮毛厂","image_url":"//cbu01.alicdn.com/img/ibank/2017/091/564/7815465190_118073014.220x220.jpg","name":"长安CS75越野SUV专用加厚汽车车衣车罩防晒防雨外套防尘隔热遮阳","price":49.92,"url":"https://detail.1688.com/offer/563771445307.html"},{"company_name":"南宫市浪淘沙皮毛厂","image_url":"//cbu01.alicdn.com/img/ibank/2017/091/564/7815465190_118073014.220x220.jpg","name":"奇瑞瑞虎3越野SUV专用车衣车罩新瑞虎3X汽车外套加厚防晒防雨隔热","price":49.92,"url":"https://detail.1688.com/offer/563835090609.html"},{"company_name":"南宫市浪淘沙皮毛厂","image_url":"//cbu01.alicdn.com/img/ibank/2017/091/564/7815465190_118073014.220x220.jpg","name":"上海大众新朗逸专用车衣车罩防晒防雨郎逸汽车套子遮阳隔热盖车布","price":49.92,"url":"https://detail.1688.com/offer/563831258993.html"},{"company_name":"南宫市浪淘沙皮毛厂","image_url":"//cbu01.alicdn.com/img/ibank/2017/091/564/7815465190_118073014.220x220.jpg","name":"新现代ix35 X25名图悦动瑞纳朗动瑞奕领动途胜防雨防晒汽车衣车罩","price":49.92,"url":"https://detail.1688.com/offer/563840038169.html"},{"company_name":"南宫市浪淘沙皮毛厂","image_url":"//cbu01.alicdn.com/img/ibank/2017/091/564/7815465190_118073014.220x220.jpg","name":"2016款新比亚迪F3车衣车罩四季专用防晒防雨防尘遮阳罩BYD汽车套","price":49.92,"url":"https://detail.1688.com/offer/563832266932.html"},{"company_name":"南宫市浪淘沙皮毛厂","image_url":"//cbu01.alicdn.com/img/ibank/2016/883/555/3605555388_118073014.search.jpg","name":"浪淘沙冬季汽车羊毛坐垫小三件套沙发垫羊毛床毯定制厂家批发定做","price":163.2,"url":"https://detail.1688.com/offer/541200731277.html"},{"company_name":"南宫市浪淘沙皮毛厂","image_url":"//cbu01.alicdn.com/img/ibank/2016/207/872/3667278702_118073014.search.jpg","name":"汽车羊毛坐垫 小三件套 单个坐垫汽车坐垫冬季沙发垫批发定做包邮","price":280.0,"url":"https://detail.1688.com/offer/35308726692.html"},{"company_name":"南宫市浪淘沙皮毛厂","image_url":"//cbu01.alicdn.com/img/ibank/2016/207/872/3667278702_118073014.search.jpg","name":"汽车坐垫用品厂家冬季加热纯羊毛皮毛一体毛绒单片座垫套小三件套","price":30.6,"url":"https://detail.1688.com/offer/1298968180.html"},{"company_name":"南宫市浪淘沙皮毛厂","image_url":"//cbu01.alicdn.com/img/ibank/2013/418/380/986083814_118073014.search.jpg","name":"浪淘沙 把套 方向盘套冬汽车把套 羊毛方向盘套一件代发厂家直销","price":40.0,"url":"https://detail.1688.com/offer/1293170031.html"},{"company_name":"南宫市浪淘沙皮毛厂","image_url":"//cbu01.alicdn.com/img/ibank/2016/742/322/3748223247_118073014.search.jpg","name":"汽车坐垫用品冬季迈腾b8羊毛坐垫座垫厂家靠背一件代发专车专用","price":385.05,"url":"https://detail.1688.com/offer/1286253567.html"},{"company_name":"南宫市浪淘沙皮毛厂","image_url":"//cbu01.alicdn.com/img/ibank/2015/029/657/2366756920_118073014.search.jpg","name":"厂家直销外贸羊毛单人双人床毯地垫飘窗地毯沙发垫椅垫定做包邮","price":968.0,"url":"https://detail.1688.com/offer/521119557738.html"},{"company_name":"南宫市浪淘沙皮毛厂","image_url":"//cbu01.alicdn.com/img/ibank/2013/192/076/980670291_118073014.search.jpg","name":"浪淘沙 把套 羊毛方向盘套 新款羊毛把套 汽车方向盘套厂家批发","price":39.0,"url":"https://detail.1688.com/offer/1282037957.html"},{"company_name":"南宫市浪淘沙皮毛厂","image_url":"//cbu01.alicdn.com/img/ibank/2018/116/935/8589539611_118073014.summ.jpg","name":"欧式澳洲仿羊毛地毯沙发圆形爬行办公室飘窗客厅卧室床边垫毯定制","price":6.76,"url":"https://detail.1688.com/offer/565428218627.html"},{"company_name":"南宫市浪淘沙皮毛厂","image_url":"//cbu01.alicdn.com/img/ibank/2018/565/892/8561298565_118073014.summ.jpg","name":"泡沫壶水枪水管高压清洗洗车金属家用浇花乳胶伸缩喷枪塑料套装","price":18.0,"url":"https://detail.1688.com/offer/565435209699.html"},{"company_name":"南宫市浪淘沙皮毛厂","image_url":"//cbu01.alicdn.com/img/ibank/2018/392/699/8816996293_118073014.summ.jpg","name":"厂家直销汽车小方垫前座单垫沙发座椅垫真羊皮羊毛一体车垫","price":32.0,"url":"https://detail.1688.com/offer/568517914309.html"},{"company_name":"南宫市浪淘沙皮毛厂","image_url":"//cbu01.alicdn.com/img/ibank/2018/360/851/8654158063_118073014.summ.jpg","name":"汽车椅背餐桌 车载后座收纳挂袋多功能置物袋电脑包 汽车用品批发","price":21.42,"url":"https://detail.1688.com/offer/566394858485.html"},{"company_name":"南宫市浪淘沙皮毛厂","image_url":"//cbu01.alicdn.com/img/ibank/2018/932/023/8530320239_118073014.summ.jpg","name":"新款皮革绗秀大包围汽车脚垫全包围连体专车专用脚垫批发车型齐全","price":289.0,"url":"https://detail.1688.com/offer/565075686957.html"},{"company_name":"南宫市浪淘沙皮毛厂","image_url":"//cbu01.alicdn.com/img/ibank/2018/065/439/8052934560_118073014.summ.jpg","name":"2017新款四季通用荞麦壳汽车座垫 秋季汽车座垫 丝绒两面汽车坐垫","price":151.0,"url":"https://detail.1688.com/offer/563619014860.html"},{"company_name":"南宫市浪淘沙皮毛厂","image_url":"//cbu01.alicdn.com/img/ibank/2018/528/860/8750068825_118073014.summ.jpg","name":"压痕昂克赛拉中华普瑞维亚大全包围专车专用通用地毯汽车地胶脚垫","price":115.0,"url":"https://detail.1688.com/offer/567569785999.html"},{"company_name":"南宫市浪淘沙皮毛厂","image_url":"//cbu01.alicdn.com/img/ibank/2018/904/447/8669744409_118073014.summ.jpg","name":"皮革汽车收纳袋座椅挂袋储物袋车用车载椅背置物袋车内饰品用品","price":21.0,"url":"https://detail.1688.com/offer/566205392672.html"},{"company_name":"南宫市浪淘沙皮毛厂","image_url":"//cbu01.alicdn.com/img/ibank/2016/207/872/3667278702_118073014.summ.jpg","name":"汽车坐垫用品厂家冬季加热纯羊毛皮毛一体毛绒单片座垫套小三件套","price":30.6,"url":"https://detail.1688.com/offer/1298968180.html"},{"company_name":"南宫市浪淘沙皮毛厂","image_url":"//cbu01.alicdn.com/img/ibank/2017/091/564/7815465190_118073014.summ.jpg","name":"三公斤铝膜汽车套子车衣棉绒加厚丰田现代冬季防水盗冻雪车罩车衣","price":58.41,"url":"https://detail.1688.com/offer/1286454384.html"},{"company_name":"南宫市浪淘沙皮毛厂","image_url":"//cbu01.alicdn.com/img/ibank/2013/837/128/946821738_118073014.summ.jpg","name":"羊毛把套 冬季 方向盘套 新款羊毛把套 汽车方向盘套 厂家批发","price":6.8,"url":"https://detail.1688.com/offer/1282791892.html"},{"company_name":"南宫市浪淘沙皮毛厂","image_url":"//cbu01.alicdn.com/img/ibank/2017/212/025/7271520212_118073014.summ.jpg","name":"汽车坐垫用品冬季加热羊毛羊绒靠背皮毛一体三件套单个厂家直销","price":189.3,"url":"https://detail.1688.com/offer/560096674639.html"},{"company_name":"南宫市浪淘沙皮毛厂","image_url":"//cbu01.alicdn.com/img/ibank/2016/207/872/3667278702_118073014.summ.jpg","name":"汽车羊毛坐垫 小三件套 单个坐垫汽车坐垫冬季沙发垫批发定做包邮","price":280.0,"url":"https://detail.1688.com/offer/35308726692.html"},{"company_name":"南宫市浪淘沙皮毛厂","image_url":"//cbu01.alicdn.com/img/ibank/2017/212/025/7271520212_118073014.summ.jpg","name":"汽车用品冬季新款毛绒座垫羊毛汽车坐垫冬季坐垫迈腾b8一件代发","price":189.3,"url":"https://detail.1688.com/offer/559943800139.html"},{"company_name":"南宫市浪淘沙皮毛厂","image_url":"//cbu01.alicdn.com/img/ibank/2018/565/892/8561298565_118073014.summ.jpg","name":"泡沫壶水枪水管高压清洗洗车金属家用浇花乳胶伸缩喷枪塑料套装","price":18.0,"url":"https://detail.1688.com/offer/565435209699.html"},{"company_name":"南宫市浪淘沙皮毛厂","image_url":"//cbu01.alicdn.com/img/ibank/2018/116/935/8589539611_118073014.summ.jpg","name":"欧式澳洲仿羊毛地毯沙发圆形爬行办公室飘窗客厅卧室床边垫毯定制","price":6.76,"url":"https://detail.1688.com/offer/565428218627.html"}]}